[
  [
    {
      "artist": "3pac",
      "title": "NEVER BEEN A HO",
      "featured": null,
      "producer": [
        "3pac"
      ],
      "audioLink": "http://www.youtube.com/watch?v=FjyaY1mW5oM"
    },
    {
      "artist": "3pac",
      "title": "WINNIN'",
      "featured": null,
      "producer": [
        "Acidonthattrack"
      ],
      "audioLink": "https://soundcloud.com/3pac-1/winnin-prod-by-acidonthattrack"
    },
    {
      "artist": "3pac",
      "title": "SWAG LIKE OSAMA",
      "featured": null,
      "producer": [
        "3pac"
      ],
      "audioLink": "https://soundcloud.com/3pac-1/swag-like-osama"
    },
    {
      "artist": "3pac",
      "title": "JULIUS CAESAR",
      "featured": null,
      "producer": [
        "Acidonthattrack"
      ],
      "audioLink": "http://www.youtube.com/watch?v=egD8nI6XviI"
    },
    {
      "artist": "3pac",
      "title": "SWAGGIN' LIKE ROMNEY",
      "featured": null,
      "producer": [
        "Marvin Cruz"
      ],
      "audioLink": "https://soundcloud.com/3pac-1/swaggin-like-romney-prod-by"
    },
    {
      "artist": "3pac",
      "title": "WHITE NIGGA",
      "featured": null,
      "producer": [
        "Shadowville Productions"
      ],
      "audioLink": "https://soundcloud.com/3pac-1/3pac-white-nigga"
    },
    {
      "artist": "3pac",
      "title": "RICH WHITE MAN MARK CUBAN",
      "featured": null,
      "producer": [
        "DaVinci On The Track"
      ],
      "audioLink": "https://soundcloud.com/3pac-1/rich-white-man-mark-cuban"
    }
  ],
  [
    {
      "artist": "3pac",
      "title": "NEVER BEEN A HO",
      "featured": null,
      "producer": [
        "3pac"
      ],
      "audioLink": "http://www.youtube.com/watch?v=FjyaY1mW5oM"
    },
    {
      "artist": "3pac",
      "title": "SWAG LIKE OSAMA",
      "featured": null,
      "producer": [
        "3pac"
      ],
      "audioLink": "https://soundcloud.com/3pac-1/swag-like-osama"
    },
    {
      "artist": "3pac",
      "title": "I DON'T GIVE A HOOT (ZERO HOOTS FREESTYLE)",
      "featured": null,
      "producer": [
        "3pac"
      ],
      "audioLink": "https://soundcloud.com/3pac-1/i-dont-give-a-hoot"
    }
  ],
  [
    {
      "artist": "3pac",
      "title": "Son",
      "featured": null,
      "producer": [
        "Killah Kibba"
      ],
      "audioLink": "https://soundcloud.com/john-counselman/kamy-sonnn-prod-by-kamy-psm"
    },
    {
      "artist": "3pac",
      "title": "Sonnn",
      "featured": null,
      "producer": [
        "Kamy"
      ],
      "audioLink": null
    }
  ]
]