[
  [
    {
      "artist": "1000mods",
      "title": "Navy in Alice",
      "featured": null,
      "producer": null,
      "audioLink": "http://www.youtube.com/watch?v=_h9lQmOayy8"
    },
    {
      "artist": "1000mods",
      "title": "Vidage",
      "featured": null,
      "producer": null,
      "audioLink": "https://soundcloud.com/1000mods/vidage"
    },
    {
      "artist": "1000mods",
      "title": "Road To Burn",
      "featured": null,
      "producer": null,
      "audioLink": "https://soundcloud.com/1000mods/road-to-burn"
    }
  ]
]