[
  {
    "artist": "Just Jack",
    "title": "Embers",
    "featured": null,
    "producer": [
      "Jay Reynolds",
      "Just Jack"
    ],
    "audioLink": "http://www.youtube.com/watch?v=8cBQha9csyw"
  },
  {
    "artist": "Just Jack",
    "title": "Blood",
    "featured": null,
    "producer": [
      "Jay Reynolds",
      "Just Jack"
    ],
    "audioLink": "http://www.youtube.com/watch?v=PNq6SuMgdFU"
  },
  {
    "artist": "Just Jack",
    "title": "Snowflakes",
    "featured": null,
    "producer": [
      "Jay Reynolds",
      "Just Jack"
    ],
    "audioLink": "http://www.youtube.com/watch?v=2CpuC2kAo18"
  },
  {
    "artist": "Just Jack",
    "title": "Snapshot Memories",
    "featured": null,
    "producer": [
      "Jay Reynolds",
      "Just Jack"
    ],
    "audioLink": "http://www.youtube.com/watch?v=7LOIlyu_Bvs"
  },
  {
    "artist": "Just Jack",
    "title": "Writer's Block",
    "featured": null,
    "producer": [
      "Jay Reynolds",
      "Just Jack"
    ],
    "audioLink": "http://www.youtube.com/watch?v=16fBF3Bgd3M"
  },
  {
    "artist": "Just Jack",
    "title": "Glory Days",
    "featured": null,
    "producer": [
      "Jay Reynolds",
      "Just Jack"
    ],
    "audioLink": "http://www.youtube.com/watch?v=-hKKgPYYt7Y"
  },
  {
    "artist": "Just Jack",
    "title": "Starz in their Eyes",
    "featured": null,
    "producer": [
      "Jay Reynolds",
      "Just Jack"
    ],
    "audioLink": "http://www.youtube.com/watch?v=H9RunljdHow"
  },
  {
    "artist": "Just Muz",
    "title": "Find No Enemy (Remix)",
    "featured": null,
    "producer": null,
    "audioLink": "http://www.youtube.com/watch?v=g2hdqDkVyD4"
  },
  {
    "artist": "Just Muz",
    "title": "Me & My Conscience",
    "featured": null,
    "producer": null,
    "audioLink": null
  },
  {
    "artist": "Just Muz",
    "title": "Fly Me To The Moon",
    "featured": null,
    "producer": null,
    "audioLink": null
  },
  {
    "artist": "Just Muz",
    "title": "Mr. Invisible",
    "featured": null,
    "producer": null,
    "audioLink": null
  },
  {
    "artist": "Just Muz",
    "title": "Distorted Truth",
    "featured": null,
    "producer": null,
    "audioLink": null
  },
  {
    "artist": "Just Muz",
    "title": "Souled Out",
    "featured": null,
    "producer": null,
    "audioLink": null
  },
  {
    "artist": "Just Muz",
    "title": "Outro-Visible",
    "featured": null,
    "producer": null,
    "audioLink": null
  },
  {
    "artist": "Just Muz",
    "title": "A Violent Culture?",
    "featured": null,
    "producer": null,
    "audioLink": null
  },
  {
    "artist": "Just Muz",
    "title": "Intro-Visible",
    "featured": null,
    "producer": null,
    "audioLink": null
  },
  {
    "artist": "Just Muz",
    "title": "Pink Matter (Remix)",
    "featured": null,
    "producer": null,
    "audioLink": "http://www.youtube.com/watch?v=poW2b6SoUyc"
  },
  {
    "artist": "Just Muz",
    "title": "2011 Till Infinity",
    "featured": null,
    "producer": null,
    "audioLink": "http://www.youtube.com/watch?v=hzqXUc6-R0Y"
  },
  {
    "artist": "Justus",
    "title": "Zeichentrick",
    "featured": [
      "Kool Savas"
    ],
    "producer": null,
    "audioLink": "http://www.youtube.com/watch?v=_BbZQ6k5g_0"
  },
  {
    "artist": "Justus",
    "title": "Besser als es ist",
    "featured": null,
    "producer": [
      "Martin B."
    ],
    "audioLink": "http://www.youtube.com/watch?v=70gn33_gpFM"
  },
  {
    "artist": "Justus",
    "title": "Judgmental",
    "featured": null,
    "producer": null,
    "audioLink": "http://www.youtube.com/watch?v=ZwOYZYgUlOM"
  },
  {
    "artist": "Justus",
    "title": "Zeichen und Muster",
    "featured": null,
    "producer": [
      "Illo"
    ],
    "audioLink": null
  },
  {
    "artist": "Justus",
    "title": "Pures Gold",
    "featured": null,
    "producer": null,
    "audioLink": null
  },
  {
    "artist": "Justus",
    "title": "Der Große Diktator",
    "featured": [
      "Maria"
    ],
    "producer": null,
    "audioLink": null
  },
  {
    "artist": "Justus",
    "title": "Dreck",
    "featured": null,
    "producer": null,
    "audioLink": null
  },
  {
    "artist": "Juvenile",
    "title": "Ha",
    "featured": null,
    "producer": [
      "Mannie Fresh"
    ],
    "audioLink": "http://www.youtube.com/watch?v=Ww9VlmXKYgs"
  },
  {
    "artist": "Juvenile",
    "title": "Gone Ride With Me",
    "featured": null,
    "producer": [
      "Mannie Fresh"
    ],
    "audioLink": null
  },
  {
    "artist": "Juvenile",
    "title": "Flossin Season",
    "featured": [
      "B.G.",
      "Big Tymers"
    ],
    "producer": [
      "Mannie Fresh"
    ],
    "audioLink": "http://www.youtube.com/watch?v=3VERsI55HWg"
  },
  {
    "artist": "Juvenile",
    "title": "Ghetto Children",
    "featured": null,
    "producer": [
      "Mannie Fresh"
    ],
    "audioLink": null
  },
  {
    "artist": "Juvenile",
    "title": "Follow Me Now",
    "featured": null,
    "producer": [
      "Mannie Fresh"
    ],
    "audioLink": null
  },
  {
    "artist": "Juvenile",
    "title": "Welcome 2 the Nolia",
    "featured": [
      "Turk"
    ],
    "producer": [
      "Mannie Fresh"
    ],
    "audioLink": null
  },
  {
    "artist": "Juvenile",
    "title": "U.P.T",
    "featured": [
      "Birdman",
      "Hot Boys"
    ],
    "producer": [
      "Mannie Fresh"
    ],
    "audioLink": null
  },
  {
    "artist": "Juvenile",
    "title": "Run For It",
    "featured": [
      "Lil Wayne"
    ],
    "producer": [
      "Mannie Fresh"
    ],
    "audioLink": "http://www.youtube.com/watch?v=01MZts7CZ1Y"
  },
  {
    "artist": "Juvenile",
    "title": "Ha (Hot Boy Remix)",
    "featured": [
      "Hot Boys"
    ],
    "producer": [
      "Mannie Fresh"
    ],
    "audioLink": "http://www.youtube.com/watch?v=QwSytyvNfqQ"
  },
  {
    "artist": "Juvenile",
    "title": "Rich Niggaz",
    "featured": [
      "Lil Wayne",
      "PapaRue",
      "Turk"
    ],
    "producer": [
      "Mannie Fresh"
    ],
    "audioLink": "http://www.youtube.com/watch?v=GtK0Fg5wPI4"
  },
  {
    "artist": "Juvenile",
    "title": "Back That Azz Up",
    "featured": [
      "Lil Wayne",
      "Mannie Fresh"
    ],
    "producer": [
      "Mannie Fresh"
    ],
    "audioLink": "https://soundcloud.com/jdsanchez3/sets/juvenile-back-that-azz-up"
  },
  {
    "artist": "Juvenile",
    "title": "Off Top",
    "featured": [
      "Big Tymers"
    ],
    "producer": [
      "Mannie Fresh"
    ],
    "audioLink": null
  },
  {
    "artist": "Juvenile",
    "title": "After Cash Money Concert",
    "featured": null,
    "producer": [
      "Mannie Fresh"
    ],
    "audioLink": null
  },
  {
    "artist": "Juvenile",
    "title": "400 Degreez",
    "featured": null,
    "producer": [
      "Mannie Fresh"
    ],
    "audioLink": "http://www.youtube.com/watch?v=sI4WtT0Brq4"
  },
  {
    "artist": "Juvenile",
    "title": "Juvenile on Fire",
    "featured": null,
    "producer": [
      "Mannie Fresh"
    ],
    "audioLink": null
  },
  {
    "artist": "Juvenile",
    "title": "Ha (Remix)",
    "featured": [
      "Jay Z"
    ],
    "producer": [
      "Mannie Fresh"
    ],
    "audioLink": "http://www.youtube.com/watch?v=yRZvemxAYAc"
  },
  {
    "artist": "Juvenile",
    "title": "Drop That Azz",
    "featured": null,
    "producer": null,
    "audioLink": "http://www.youtube.com/watch?v=GIHL2NI-ssY"
  },
  {
    "artist": "Juvenile",
    "title": "G-ing Men",
    "featured": null,
    "producer": [
      "Leroy \"Precise\" Edwards"
    ],
    "audioLink": null
  },
  {
    "artist": "Juvenile",
    "title": "Pass Azz Nigga",
    "featured": null,
    "producer": [
      "Leroy \"Precise\" Edwards"
    ],
    "audioLink": null
  },
  {
    "artist": "Juvenile",
    "title": "U Can't See Me",
    "featured": null,
    "producer": [
      "Leroy \"Precise\" Edwards"
    ],
    "audioLink": null
  },
  {
    "artist": "Juvenile",
    "title": "Shake Dat Azz (If You're A Player)",
    "featured": null,
    "producer": [
      "Leroy \"Precise\" Edwards"
    ],
    "audioLink": null
  },
  {
    "artist": "Juvenile",
    "title": "Conversation With Tha Man Above",
    "featured": null,
    "producer": [
      "Leroy \"Precise\" Edwards"
    ],
    "audioLink": null
  },
  {
    "artist": "Juvenile",
    "title": "U Understand",
    "featured": null,
    "producer": [
      "Mannie Fresh"
    ],
    "audioLink": "http://www.youtube.com/watch?v=QT6lrRUzjW4"
  },
  {
    "artist": "Juvenile",
    "title": "Fuck That Nigga",
    "featured": [
      "B.G."
    ],
    "producer": [
      "Mannie Fresh"
    ],
    "audioLink": null
  },
  {
    "artist": "Juvenile",
    "title": "A Million and One Things",
    "featured": [
      "Hot Boys"
    ],
    "producer": [
      "Mannie Fresh"
    ],
    "audioLink": null
  },
  {
    "artist": "Juvenile",
    "title": "Take Them 5",
    "featured": null,
    "producer": [
      "Mannie Fresh"
    ],
    "audioLink": null
  },
  {
    "artist": "Juvenile",
    "title": "G-Code",
    "featured": [
      "Lil Wayne"
    ],
    "producer": [
      "Mannie Fresh"
    ],
    "audioLink": "http://www.youtube.com/watch?v=JtqJM3HdIwE"
  },
  {
    "artist": "Juvenile",
    "title": "Something Got 2 Shake",
    "featured": [
      "Big Tymers"
    ],
    "producer": [
      "Mannie Fresh"
    ],
    "audioLink": null
  },
  {
    "artist": "Juvenile",
    "title": "Da Magnolia",
    "featured": [
      "Mannie Fresh"
    ],
    "producer": [
      "Mannie Fresh"
    ],
    "audioLink": null
  },
  {
    "artist": "Juvenile",
    "title": "Catch Your Cut",
    "featured": [
      "B.G."
    ],
    "producer": [
      "Mannie Fresh"
    ],
    "audioLink": null
  },
  {
    "artist": "Juvenile",
    "title": "Lil Boyz",
    "featured": [
      "Big Tymers",
      "Lil Wayne"
    ],
    "producer": [
      "Mannie Fresh"
    ],
    "audioLink": null
  },
  {
    "artist": "Juvenile",
    "title": "Get it Right",
    "featured": [
      "B.G.",
      "Lil Wayne"
    ],
    "producer": [
      "Mannie Fresh"
    ],
    "audioLink": null
  },
  {
    "artist": "Juvenile",
    "title": "Never Had Shit",
    "featured": [
      "B.G.",
      "Birdman",
      "Turk"
    ],
    "producer": [
      "Mannie Fresh"
    ],
    "audioLink": null
  },
  {
    "artist": "Juvenile",
    "title": "I Got That Fire",
    "featured": [
      "Mannie Fresh"
    ],
    "producer": [
      "Mannie Fresh"
    ],
    "audioLink": "http://www.youtube.com/watch?v=afHNLtIJNmY"
  },
  {
    "artist": "Juvenile",
    "title": "Tha Man",
    "featured": [
      "Turk"
    ],
    "producer": [
      "Mannie Fresh"
    ],
    "audioLink": null
  },
  {
    "artist": "Juvenile",
    "title": "March Nigga Step",
    "featured": [
      "Mannie Fresh"
    ],
    "producer": [
      "Mannie Fresh"
    ],
    "audioLink": null
  },
  {
    "artist": "Juvenile",
    "title": "Guerrilla",
    "featured": [
      "B.G."
    ],
    "producer": [
      "Mannie Fresh"
    ],
    "audioLink": null
  },
  {
    "artist": "Juvenile",
    "title": "Intro",
    "featured": null,
    "producer": [
      "AD Future"
    ],
    "audioLink": null
  },
  {
    "artist": "Juvenile",
    "title": "In My Life",
    "featured": [
      "Mannie Fresh"
    ],
    "producer": [
      "Mannie Fresh"
    ],
    "audioLink": null
  },
  {
    "artist": "Juvenile",
    "title": "Enemy Turf",
    "featured": null,
    "producer": [
      "Grizz"
    ],
    "audioLink": null
  },
  {
    "artist": "Juvenile",
    "title": "Bounce Back",
    "featured": [
      "Birdman"
    ],
    "producer": [
      "Mannie Fresh"
    ],
    "audioLink": null
  },
  {
    "artist": "Juvenile",
    "title": "Down South Posted",
    "featured": [
      "Skip",
      "Wacko"
    ],
    "producer": [
      "Slice Tee"
    ],
    "audioLink": null
  },
  {
    "artist": "Juvenile",
    "title": "It Ain't Mines",
    "featured": null,
    "producer": [
      "Mannie Fresh"
    ],
    "audioLink": null
  },
  {
    "artist": "Juvenile",
    "title": "Numb Numb",
    "featured": null,
    "producer": [
      "Grizz"
    ],
    "audioLink": "http://www.youtube.com/watch?v=uxl-ypCr5Us"
  },
  {
    "artist": "Juvenile",
    "title": "Lil' Daddy",
    "featured": [
      "Birdman"
    ],
    "producer": [
      "Mannie Fresh"
    ],
    "audioLink": null
  },
  {
    "artist": "Juvenile",
    "title": "Fuckin' With Me",
    "featured": [
      "Skip",
      "Wacko"
    ],
    "producer": [
      "Slice Tee"
    ],
    "audioLink": null
  },
  {
    "artist": "Juvenile",
    "title": "Cock It",
    "featured": null,
    "producer": [
      "Mannie Fresh"
    ],
    "audioLink": null
  },
  {
    "artist": "Juvenile",
    "title": "Juve the Great",
    "featured": null,
    "producer": [
      "Black Jeruz",
      "Sha Money XL"
    ],
    "audioLink": null
  },
  {
    "artist": "Juvenile",
    "title": "Head in Advance",
    "featured": null,
    "producer": [
      "Slice Tee"
    ],
    "audioLink": null
  },
  {
    "artist": "Juvenile",
    "title": "For Everybody",
    "featured": [
      "Skip",
      "Wacko"
    ],
    "producer": [
      "KLC"
    ],
    "audioLink": null
  },
  {
    "artist": "Juvenile",
    "title": "Slow Motion",
    "featured": [
      "Soulja Slim"
    ],
    "producer": [
      "Dani Kartel"
    ],
    "audioLink": "http://www.youtube.com/watch?v=KvzemQPAIIo"
  },
  {
    "artist": "Juvenile",
    "title": "What's Up Wit Dat",
    "featured": [
      "Big Tymers",
      "Lil Wayne"
    ],
    "producer": null,
    "audioLink": null
  },
  {
    "artist": "Juvenile",
    "title": "Intro - Let's Roll",
    "featured": [
      "Big Tymers",
      "Mikkey Halsted"
    ],
    "producer": [
      "Mannie Fresh"
    ],
    "audioLink": null
  },
  {
    "artist": "Juvenile",
    "title": "Set It Off",
    "featured": null,
    "producer": [
      "Mannie Fresh"
    ],
    "audioLink": "http://www.youtube.com/watch?v=IbplL8kD4Pc"
  },
  {
    "artist": "Juvenile",
    "title": "H.B. HeadBusta",
    "featured": null,
    "producer": [
      "Mannie Fresh"
    ],
    "audioLink": null
  },
  {
    "artist": "Juvenile",
    "title": "4 Minutes",
    "featured": [
      "Hot Boys"
    ],
    "producer": [
      "Mannie Fresh"
    ],
    "audioLink": null
  },
  {
    "artist": "Juvenile",
    "title": "My Life",
    "featured": [
      "TQ"
    ],
    "producer": [
      "Mannie Fresh"
    ],
    "audioLink": null
  },
  {
    "artist": "Juvenile",
    "title": "Get Your Hustle On",
    "featured": [
      "Big Tymers"
    ],
    "producer": [
      "Mannie Fresh"
    ],
    "audioLink": null
  },
  {
    "artist": "Juvenile",
    "title": "Sunshine",
    "featured": [
      "B.G.",
      "Big Tymers",
      "Lil Wayne"
    ],
    "producer": [
      "Mannie Fresh"
    ],
    "audioLink": null
  },
  {
    "artist": "Juvenile",
    "title": "Be Gone",
    "featured": [
      "Big Tymers"
    ],
    "producer": [
      "Mannie Fresh"
    ],
    "audioLink": "http://www.youtube.com/watch?v=DwAJ2OLFk8g"
  },
  {
    "artist": "Juvenile",
    "title": "Mamma Got Ass",
    "featured": null,
    "producer": [
      "Mannie Fresh"
    ],
    "audioLink": null
  },
  {
    "artist": "Juvenile",
    "title": "They Lied",
    "featured": [
      "Big Tymers"
    ],
    "producer": [
      "Mannie Fresh"
    ],
    "audioLink": null
  },
  {
    "artist": "Juvenile",
    "title": "White Girl",
    "featured": [
      "Birdman",
      "Lil Wayne"
    ],
    "producer": [
      "Mannie Fresh"
    ],
    "audioLink": null
  },
  {
    "artist": "Juvenile",
    "title": "In Ya Ass",
    "featured": null,
    "producer": [
      "Mannie Fresh"
    ],
    "audioLink": null
  },
  {
    "artist": "Juvenile",
    "title": "Set it Off (Radio Remix)",
    "featured": [
      "Birdman",
      "Lil Wayne",
      "Turk"
    ],
    "producer": [
      "Mannie Fresh"
    ],
    "audioLink": null
  },
  {
    "artist": "Juvenile",
    "title": "In the Nolia",
    "featured": null,
    "producer": [
      "Mannie Fresh"
    ],
    "audioLink": null
  },
  {
    "artist": "Juvenile",
    "title": "What U Scared 4",
    "featured": [
      "Lil Wayne"
    ],
    "producer": [
      "Mannie Fresh"
    ],
    "audioLink": null
  },
  {
    "artist": "Juvenile",
    "title": "Outro - Let's Go",
    "featured": [
      "Big G",
      "Birdman",
      "Lac",
      "Sickwitit",
      "Steppa"
    ],
    "producer": [
      "Mannie Fresh"
    ],
    "audioLink": null
  },
  {
    "artist": "Juvenile",
    "title": "U Don't Wanna",
    "featured": [
      "Big Tymers",
      "Hot Boys"
    ],
    "producer": null,
    "audioLink": null
  },
  {
    "artist": "Juvenile",
    "title": "Get Ya Hustle On",
    "featured": null,
    "producer": [
      "Sinista"
    ],
    "audioLink": null
  },
  {
    "artist": "Juvenile",
    "title": "Around the Way",
    "featured": null,
    "producer": [
      "Sinista"
    ],
    "audioLink": null
  },
  {
    "artist": "Juvenile",
    "title": "Sets Go Up",
    "featured": [
      "Wacko"
    ],
    "producer": [
      "Scott Storch"
    ],
    "audioLink": "https://soundcloud.com/andiazz/06-juvenile-sets-go-up"
  },
  {
    "artist": "Juvenile",
    "title": "Rodeo",
    "featured": null,
    "producer": [
      "Cool",
      "Dre"
    ],
    "audioLink": "http://www.youtube.com/watch?v=S5ATUCocIyc"
  },
  {
    "artist": "Juvenile",
    "title": "What's Happenin'",
    "featured": null,
    "producer": [
      "Sinista"
    ],
    "audioLink": "http://www.youtube.com/watch?v=SjSrefosynE"
  },
  {
    "artist": "Juvenile",
    "title": "Loose Booty",
    "featured": [
      "8Ball",
      "Skip"
    ],
    "producer": [
      "Stormy Day"
    ],
    "audioLink": null
  },
  {
    "artist": "Juvenile",
    "title": "Way I Be Leanin'",
    "featured": [
      "Mike Jones",
      "Paul Wall",
      "Skip",
      "Wacko"
    ],
    "producer": [
      "Perion"
    ],
    "audioLink": null
  },
  {
    "artist": "Juvenile",
    "title": "Break a Brick Down",
    "featured": null,
    "producer": [
      "Cool",
      "Dre"
    ],
    "audioLink": null
  },
  {
    "artist": "Juvenile",
    "title": "Who's Ya Daddy",
    "featured": null,
    "producer": [
      "Sinista"
    ],
    "audioLink": null
  },
  {
    "artist": "Juvenile",
    "title": "I Know You Know",
    "featured": [
      "Trey Songz"
    ],
    "producer": [
      "Happy Perez"
    ],
    "audioLink": null
  },
  {
    "artist": "Juvenile",
    "title": "Keep Talkin'",
    "featured": [
      "Redd Eyezz",
      "Skip"
    ],
    "producer": [
      "Sinista"
    ],
    "audioLink": null
  },
  {
    "artist": "Juvenile",
    "title": "Rock Like That",
    "featured": [
      "Bun B"
    ],
    "producer": [
      "Sinista"
    ],
    "audioLink": null
  },
  {
    "artist": "Juvenile",
    "title": "Why Not",
    "featured": [
      "Skip"
    ],
    "producer": [
      "Lil Jon"
    ],
    "audioLink": "http://www.youtube.com/watch?v=LTRTDtbXQV0"
  },
  {
    "artist": "Juvenile",
    "title": "Animal",
    "featured": null,
    "producer": [
      "Mannie Fresh"
    ],
    "audioLink": null
  },
  {
    "artist": "Juvenile",
    "title": "Addicted",
    "featured": [
      "Brian McKnight"
    ],
    "producer": [
      "Brian McKnight"
    ],
    "audioLink": null
  },
  {
    "artist": "Juvenile",
    "title": "Pop U",
    "featured": [
      "Fat Joe",
      "Ludacris"
    ],
    "producer": [
      "Juvenile",
      "Mike Dean"
    ],
    "audioLink": null
  },
  {
    "artist": "Juvenile",
    "title": "Say it to Me Now",
    "featured": null,
    "producer": [
      "Scott Storch"
    ],
    "audioLink": null
  },
  {
    "artist": "Juvenile",
    "title": "Power",
    "featured": [
      "Rick Ross"
    ],
    "producer": [
      "Mannie Fresh"
    ],
    "audioLink": "http://www.youtube.com/watch?v=sCZmzvFTjgc"
  },
  {
    "artist": "Juvenile",
    "title": "Ain't What You Want",
    "featured": null,
    "producer": [
      "S-8ighty"
    ],
    "audioLink": "http://www.youtube.com/watch?v=83b2yFivFHU"
  },
  {
    "artist": "Juvenile",
    "title": "Dirty World (Remix)",
    "featured": [
      "Lil Derrick",
      "TC",
      "Turk"
    ],
    "producer": null,
    "audioLink": null
  },
  {
    "artist": "Juvenile",
    "title": "I Did That",
    "featured": [
      "B.G.",
      "Big Moe",
      "Bulletproof"
    ],
    "producer": [
      "Mannie Fresh"
    ],
    "audioLink": null
  },
  {
    "artist": "Juvenile",
    "title": "Roll With 'Em",
    "featured": [
      "Big Tymers"
    ],
    "producer": [
      "Mannie Fresh"
    ],
    "audioLink": null
  },
  {
    "artist": "Juvenile",
    "title": "Pimpinabitch",
    "featured": null,
    "producer": [
      "Mannie Fresh"
    ],
    "audioLink": null
  },
  {
    "artist": "Juvenile",
    "title": "Livin in the Projects",
    "featured": null,
    "producer": [
      "Mannie Fresh"
    ],
    "audioLink": null
  },
  {
    "artist": "Juvenile",
    "title": "Who's the M.F.",
    "featured": null,
    "producer": [
      "Mannie Fresh"
    ],
    "audioLink": "http://www.youtube.com/watch?v=jBVxJQ6nafI"
  },
  {
    "artist": "Juvenile",
    "title": "Hide Out Or Ride Out",
    "featured": [
      "Lil Wayne",
      "Turk"
    ],
    "producer": [
      "Mannie Fresh"
    ],
    "audioLink": null
  },
  {
    "artist": "Juvenile",
    "title": "Spittin' Game",
    "featured": [
      "Bulletproof",
      "Hot Boys"
    ],
    "producer": [
      "Mannie Fresh"
    ],
    "audioLink": null
  },
  {
    "artist": "Juvenile",
    "title": "3rd Ward solja",
    "featured": [
      "Magnolia Shorty",
      "Mannie Fresh"
    ],
    "producer": [
      "Mannie Fresh"
    ],
    "audioLink": "http://www.youtube.com/watch?v=SivNkYS3rGw"
  },
  {
    "artist": "Juvenile",
    "title": "Welcome 2 Tha Section",
    "featured": [
      "B.G.",
      "Bulletproof"
    ],
    "producer": [
      "Mannie Fresh"
    ],
    "audioLink": null
  },
  {
    "artist": "Juvenile",
    "title": "Money on the Couch",
    "featured": null,
    "producer": [
      "Mannie Fresh"
    ],
    "audioLink": null
  },
  {
    "artist": "Juvenile",
    "title": "That's How it be Happenin'",
    "featured": null,
    "producer": [
      "Mannie Fresh"
    ],
    "audioLink": null
  },
  {
    "artist": "Juvenile",
    "title": "Solja Rags (Radio Version)",
    "featured": null,
    "producer": [
      "Mannie Fresh"
    ],
    "audioLink": null
  },
  {
    "artist": "J Wells",
    "title": "It Don't Stop",
    "featured": [
      "J-Ro",
      "KBimean",
      "Method Man"
    ],
    "producer": null,
    "audioLink": null
  },
  {
    "artist": "J Wells",
    "title": "Let 'Em Know",
    "featured": [
      "Tha Alkaholiks",
      "Butch Cassidy",
      "Kurupt"
    ],
    "producer": null,
    "audioLink": null
  },
  {
    "artist": "J Wells",
    "title": "Tonight",
    "featured": [
      "J-Ro",
      "Kurupt"
    ],
    "producer": null,
    "audioLink": null
  },
  {
    "artist": "J.Y.",
    "title": "On My Mind",
    "featured": null,
    "producer": [
      "Hank Iving"
    ],
    "audioLink": "http://www.youtube.com/watch?v=Ijq38cbUlMw"
  },
  {
    "artist": "J.Y.",
    "title": "We All Good",
    "featured": [
      "Nipsey Hu$$le",
      "Young Scolla"
    ],
    "producer": [
      "Fortunate Ones"
    ],
    "audioLink": "http://www.youtube.com/watch?v=XJanfOldYzY"
  },
  {
    "artist": "J.Y.",
    "title": "Wave Season",
    "featured": [
      "Max B"
    ],
    "producer": [
      "Cito on the Beat"
    ],
    "audioLink": null
  },
  {
    "artist": "J-Yak",
    "title": "Hold On, Heaven",
    "featured": null,
    "producer": [
      "Hulk Hodn"
    ],
    "audioLink": null
  },
  {
    "artist": "J-Yak",
    "title": "Social Network",
    "featured": null,
    "producer": null,
    "audioLink": null
  },
  {
    "artist": "J-Yak",
    "title": "Gold Rush",
    "featured": [
      "HuckFin"
    ],
    "producer": [
      "Sango"
    ],
    "audioLink": null
  },
  {
    "artist": "J-Yak",
    "title": "Who Is",
    "featured": null,
    "producer": null,
    "audioLink": "http://www.youtube.com/watch?v=8JLfOosBSmc"
  },
  {
    "artist": "J-Yak",
    "title": "Valley Kids",
    "featured": null,
    "producer": null,
    "audioLink": "http://www.youtube.com/watch?v=jOYBc2Hd-6Q"
  },
  {
    "artist": "J-Yak",
    "title": "The Last Intro",
    "featured": null,
    "producer": [
      "Oathery"
    ],
    "audioLink": null
  },
  {
    "artist": "J-Zone",
    "title": "The Zone Mission (Part VIII)",
    "featured": null,
    "producer": null,
    "audioLink": null
  },
  {
    "artist": "J-Zone",
    "title": "No Consequences",
    "featured": [
      "Huggy Bear"
    ],
    "producer": null,
    "audioLink": null
  },
  {
    "artist": "J-Zone",
    "title": "The Smurf Syndrome",
    "featured": null,
    "producer": null,
    "audioLink": null
  },
  {
    "artist": "J-Zone",
    "title": "Orphan Babies",
    "featured": [
      "Huggy Bear"
    ],
    "producer": [
      "J-Zone"
    ],
    "audioLink": null
  },
  {
    "artist": "J-Zone",
    "title": "Recess",
    "featured": [
      "Al Shid"
    ],
    "producer": null,
    "audioLink": null
  },
  {
    "artist": "J-Zone",
    "title": "The First Day of School",
    "featured": [
      "Al Shid"
    ],
    "producer": null,
    "audioLink": null
  },
  {
    "artist": "J-Zone",
    "title": "$poiled Rotten",
    "featured": [
      "Celph Titled"
    ],
    "producer": [
      "J-Zone"
    ],
    "audioLink": null
  },
  {
    "artist": "J-Zone",
    "title": "A Friendly Game of Basketball",
    "featured": null,
    "producer": null,
    "audioLink": "http://www.youtube.com/watch?v=CcSmv5BcehQ"
  },
  {
    "artist": "J-Zone",
    "title": "Greater Later",
    "featured": [
      "Devin The Dude"
    ],
    "producer": null,
    "audioLink": null
  },
  {
    "artist": "J-Zone",
    "title": "Kill Pretty",
    "featured": null,
    "producer": [
      "J-Zone"
    ],
    "audioLink": null
  },
  {
    "artist": "J-Zone",
    "title": "The Zone Mission",
    "featured": null,
    "producer": null,
    "audioLink": null
  },
  {
    "artist": "J-Zone",
    "title": "Candy Razors",
    "featured": [
      "Huggy Bear"
    ],
    "producer": [
      "J-Zone"
    ],
    "audioLink": null
  },
  {
    "artist": "J-Zone",
    "title": "Catch 22",
    "featured": [
      "Huggy Bear"
    ],
    "producer": null,
    "audioLink": null
  },
  {
    "artist": "J-Zone",
    "title": "Inauguration Day",
    "featured": null,
    "producer": null,
    "audioLink": null
  },
  {
    "artist": "J-Zone",
    "title": "Inauguration Day",
    "featured": null,
    "producer": null,
    "audioLink": null
  },
  {
    "artist": "J-Zone",
    "title": "Gadget Ho",
    "featured": null,
    "producer": [
      "J-Zone"
    ],
    "audioLink": "https://soundcloud.com/macmediapromo/j-zone-gadget-ho"
  },
  {
    "artist": "J-Zone",
    "title": "Jackin For Basquiats",
    "featured": [
      "Chief Chinchilla a.k.a. J-Zone"
    ],
    "producer": null,
    "audioLink": "http://www.youtube.com/watch?v=0LNckLUeVCo"
  },
  {
    "artist": "J-Zone",
    "title": "Q & A",
    "featured": null,
    "producer": null,
    "audioLink": null
  },
  {
    "artist": "J-Zone",
    "title": "Live from Pimp Palace East",
    "featured": [
      "Al-Shide",
      "Huggy"
    ],
    "producer": null,
    "audioLink": "http://www.youtube.com/watch?v=8BZsnAJNQuw"
  },
  {
    "artist": "J-Zone",
    "title": "Trojan War",
    "featured": [
      "Huggy Bear"
    ],
    "producer": null,
    "audioLink": null
  },
  {
    "artist": "J-Zone",
    "title": "The Bum-Bitch Ballad",
    "featured": null,
    "producer": null,
    "audioLink": "http://www.youtube.com/watch?v=tWXHokANmsQ"
  },
  {
    "artist": "J-Zone",
    "title": "No Consequences",
    "featured": [
      "Huggy Bear"
    ],
    "producer": null,
    "audioLink": null
  },
  {
    "artist": "J-Zone",
    "title": "County Check Pimpin",
    "featured": null,
    "producer": null,
    "audioLink": null
  },
  {
    "artist": "J-Zone",
    "title": "Zone for President",
    "featured": null,
    "producer": null,
    "audioLink": null
  },
  {
    "artist": "J-Zone",
    "title": "I'm Fuckin Up The Money",
    "featured": [
      "Huggy Bear"
    ],
    "producer": [
      "J-Zone"
    ],
    "audioLink": null
  },
  {
    "artist": "J-Zone",
    "title": "Jailbait Jennifer",
    "featured": [
      "Al Shid"
    ],
    "producer": null,
    "audioLink": null
  },
  {
    "artist": "J-Zone",
    "title": "Ms. Platonic Part 2",
    "featured": null,
    "producer": null,
    "audioLink": null
  },
  {
    "artist": "J-Zone",
    "title": "MetroCard Millionaires",
    "featured": [
      "Al Shid",
      "Huggy"
    ],
    "producer": null,
    "audioLink": "http://www.youtube.com/watch?v=2OHoGqtPuPY"
  },
  {
    "artist": "J-Zone",
    "title": "The Commandment$",
    "featured": null,
    "producer": null,
    "audioLink": null
  },
  {
    "artist": "J-Zone",
    "title": "5 $tar Hooptie",
    "featured": null,
    "producer": [
      "J-Zone"
    ],
    "audioLink": "http://www.youtube.com/watch?v=MW8p3wHcpDE"
  },
  {
    "artist": "J-Zone",
    "title": "38th & 8th",
    "featured": [
      "Al Shid"
    ],
    "producer": [
      "J-Zone"
    ],
    "audioLink": "http://www.youtube.com/watch?v=cWaD2VqPrvI"
  },
  {
    "artist": "J-Zone",
    "title": "Gimme, Gimme, Gimme",
    "featured": [
      "Masta Ace"
    ],
    "producer": [
      "J-Zone"
    ],
    "audioLink": null
  },
  {
    "artist": "J-Zone",
    "title": "Too Many Babies",
    "featured": null,
    "producer": null,
    "audioLink": null
  },
  {
    "artist": "J-Zone",
    "title": "Choir Practice",
    "featured": [
      "J-Ro",
      "King Tee"
    ],
    "producer": [
      "J-Zone"
    ],
    "audioLink": null
  },
  {
    "artist": "J-Zone",
    "title": "Bling Around The Collar (Fake Gold Chain)",
    "featured": null,
    "producer": [
      "J-Zone"
    ],
    "audioLink": null
  },
  {
    "artist": "J-Zone",
    "title": "Eatadiccup",
    "featured": [
      "Celph Titled"
    ],
    "producer": [
      "J-Zone"
    ],
    "audioLink": null
  },
  {
    "artist": "K19",
    "title": "Purple Gold (Black And Yellow Remix)",
    "featured": null,
    "producer": null,
    "audioLink": "http://www.youtube.com/watch?v=xjM1qx4LobU"
  },
  {
    "artist": "K19",
    "title": "Killer Remix",
    "featured": null,
    "producer": null,
    "audioLink": null
  },
  {
    "artist": "K19",
    "title": "Look At Me Now Remix",
    "featured": null,
    "producer": null,
    "audioLink": null
  },
  {
    "artist": "K19",
    "title": "Mo Money Mo Problems Remix",
    "featured": null,
    "producer": null,
    "audioLink": "http://www.youtube.com/watch?v=l4k-bb1f8P8"
  },
  {
    "artist": "K19",
    "title": "76 Bars (Moment For Life Remix)",
    "featured": null,
    "producer": null,
    "audioLink": null
  },
  {
    "artist": "K19",
    "title": "Otis Remix",
    "featured": null,
    "producer": null,
    "audioLink": null
  },
  {
    "artist": "K19",
    "title": "Unlimited (The Winner Remix)",
    "featured": null,
    "producer": null,
    "audioLink": "http://www.youtube.com/watch?v=tSaa56ZWlxk"
  },
  {
    "artist": "K19",
    "title": "I See You remix",
    "featured": null,
    "producer": null,
    "audioLink": "http://www.youtube.com/watch?v=nZMo0iv6Owo"
  },
  {
    "artist": "K19",
    "title": "Came So far",
    "featured": null,
    "producer": null,
    "audioLink": "http://www.youtube.com/watch?v=02C8jlOCeCQ"
  },
  {
    "artist": "K19",
    "title": "Im Feeling Good",
    "featured": [
      "Cassandra Thurman",
      "Jay Mixx"
    ],
    "producer": null,
    "audioLink": "http://www.youtube.com/watch?v=IBgeUPE-g4w"
  },
  {
    "artist": "K19",
    "title": "Karate Chop Remix",
    "featured": null,
    "producer": null,
    "audioLink": "https://soundcloud.com/theofficialk19/k19-karate-chop-remix"
  },
  {
    "artist": "K19",
    "title": "My Moment Remix",
    "featured": null,
    "producer": null,
    "audioLink": "http://www.youtube.com/watch?v=yuZ2NxxI-rs"
  },
  {
    "artist": "K19",
    "title": "Feet Dont Fail Me Now",
    "featured": [
      "Nygee Oliver"
    ],
    "producer": [
      "K19"
    ],
    "audioLink": "https://soundcloud.com/theofficialk19/k19-feet-dont-fail-me-now-ft-nygee-oliver"
  },
  {
    "artist": "K2",
    "title": "Scena otwarcia",
    "featured": null,
    "producer": [
      "Subbassa"
    ],
    "audioLink": "http://www.youtube.com/watch?v=jkO2nP35UYU"
  },
  {
    "artist": "K2",
    "title": "Tu Umierają Anioły",
    "featured": [
      "Dj Bambus"
    ],
    "producer": [
      "Subbassa"
    ],
    "audioLink": "http://www.youtube.com/watch?v=MaGAEki4I0M"
  },
  {
    "artist": "K2",
    "title": "Madafakin Szou",
    "featured": null,
    "producer": [
      "Subbassa"
    ],
    "audioLink": "http://www.youtube.com/watch?v=Bt5XZhEuoyw"
  },
  {
    "artist": "K2",
    "title": "Frontkick",
    "featured": [
      "Bu",
      "Cma (PL)"
    ],
    "producer": [
      "Subbassa"
    ],
    "audioLink": "http://www.youtube.com/watch?v=JuDRhh3lx2k"
  },
  {
    "artist": "K2",
    "title": "FTS",
    "featured": [
      "Kleszcz"
    ],
    "producer": null,
    "audioLink": "http://www.youtube.com/watch?v=RqjzXuyljU4"
  },
  {
    "artist": "K2",
    "title": "Scena Dramatu",
    "featured": [
      "Dj Bambus"
    ],
    "producer": [
      "Subbassa"
    ],
    "audioLink": "http://www.youtube.com/watch?v=qtVM6Oucl0k"
  },
  {
    "artist": "K2",
    "title": "Mila morska",
    "featured": null,
    "producer": [
      "Subbassa"
    ],
    "audioLink": "http://www.youtube.com/watch?v=npxGqlv1Jr8"
  },
  {
    "artist": "K2",
    "title": "Nagi Instynkt",
    "featured": null,
    "producer": [
      "Subbassa"
    ],
    "audioLink": "http://www.youtube.com/watch?v=lAo3DVIxOo0"
  },
  {
    "artist": "K2",
    "title": "1 Moment",
    "featured": [
      "Buka"
    ],
    "producer": [
      "Subbassa"
    ],
    "audioLink": "http://www.youtube.com/watch?v=RjzujFoWxY8"
  },
  {
    "artist": "K2",
    "title": "Scena Akcji",
    "featured": null,
    "producer": [
      "Jukasz"
    ],
    "audioLink": "http://www.youtube.com/watch?v=idpuTM2lXxQ"
  },
  {
    "artist": "K2",
    "title": "Polski Meksyk",
    "featured": null,
    "producer": [
      "Subbassa"
    ],
    "audioLink": "http://www.youtube.com/watch?v=JASTjXtOdJ4"
  },
  {
    "artist": "K2",
    "title": "Heroina",
    "featured": null,
    "producer": null,
    "audioLink": null
  },
  {
    "artist": "K2",
    "title": "Praggamuffin",
    "featured": null,
    "producer": [
      "Jukasz"
    ],
    "audioLink": "http://www.youtube.com/watch?v=UGawNXQtW1E"
  },
  {
    "artist": "K2",
    "title": "Taniec Z Diabłem",
    "featured": null,
    "producer": [
      "Jukasz"
    ],
    "audioLink": "http://www.youtube.com/watch?v=1HmWNRdwylg"
  },
  {
    "artist": "K2",
    "title": "Kołysanka",
    "featured": null,
    "producer": [
      "Cma (PL)",
      "Jukasz",
      "SKW"
    ],
    "audioLink": "http://www.youtube.com/watch?v=PN8vE-eM8C4"
  },
  {
    "artist": "K2",
    "title": "Granice Rzeczywistości",
    "featured": null,
    "producer": [
      "ONAA"
    ],
    "audioLink": "http://www.youtube.com/watch?v=u-aa_3Xf3qM"
  },
  {
    "artist": "K2",
    "title": "7H",
    "featured": null,
    "producer": [
      "Subbassa"
    ],
    "audioLink": "http://www.youtube.com/watch?v=ghGIyPTKlEE"
  },
  {
    "artist": "K2",
    "title": "Arkadia",
    "featured": null,
    "producer": [
      "Jukasz"
    ],
    "audioLink": "http://www.youtube.com/watch?v=sUXfNte2xvs"
  },
  {
    "artist": "K2",
    "title": "List",
    "featured": null,
    "producer": [
      "Jukasz"
    ],
    "audioLink": "http://www.youtube.com/watch?v=1GaNNKTaXX4"
  },
  {
    "artist": "K-9",
    "title": "Compton K9 Mc Eiht",
    "featured": [
      "K-9",
      "MC Eiht"
    ],
    "producer": [
      "Caligerminc",
      "Fulldeckrecords",
      "K-9",
      "Nuthouse",
      "T-nut"
    ],
    "audioLink": "https://soundcloud.com/k9compton/compton-feat-mc-eiht"
  },
  {
    "artist": "K-9",
    "title": "Diss",
    "featured": [
      "Quietude",
      "Tova"
    ],
    "producer": null,
    "audioLink": null
  },
  {
    "artist": "K-9",
    "title": "Gangsta'd Out",
    "featured": null,
    "producer": null,
    "audioLink": null
  },
  {
    "artist": "Ka",
    "title": "Years",
    "featured": null,
    "producer": [
      "DJ Preservation"
    ],
    "audioLink": null
  },
  {
    "artist": "Ka",
    "title": "Still Heir",
    "featured": null,
    "producer": [
      "DJ Preservation"
    ],
    "audioLink": null
  },
  {
    "artist": "Ka",
    "title": "Blood In My Bath, Flesh In My Tub",
    "featured": null,
    "producer": [
      "Albertz Beatz"
    ],
    "audioLink": "http://www.youtube.com/watch?v=RMkJ097uLMs"
  },
  {
    "artist": "Ka",
    "title": "My Bitches (Skit)",
    "featured": [
      "Mr. Boy"
    ],
    "producer": [
      "Albertz Beatz"
    ],
    "audioLink": "http://www.youtube.com/watch?v=MPicmbQVbA4"
  },
  {
    "artist": "Ka",
    "title": "Been't Ya Hell Crown",
    "featured": [
      "Boy Karim",
      "Mr. Boy"
    ],
    "producer": null,
    "audioLink": "http://www.youtube.com/watch?v=xJp4oWrfG2E"
  },
  {
    "artist": "Ka",
    "title": "That's Ass It's Houser",
    "featured": null,
    "producer": [
      "Lorde"
    ],
    "audioLink": null
  },
  {
    "artist": "Ka",
    "title": "Child's Play",
    "featured": null,
    "producer": [
      "Dr. Campbell"
    ],
    "audioLink": null
  },
  {
    "artist": "Ka",
    "title": "Bitches Don't Pump My Heart It",
    "featured": [
      "L.E.P.",
      "Mr. Candy"
    ],
    "producer": [
      "Dr. Campbell"
    ],
    "audioLink": null
  },
  {
    "artist": "Ka",
    "title": "Craft",
    "featured": null,
    "producer": [
      "Dr. Campbell"
    ],
    "audioLink": null
  },
  {
    "artist": "Ka",
    "title": "Chamber",
    "featured": null,
    "producer": null,
    "audioLink": "http://www.youtube.com/watch?v=4oxbBP-Ai8U"
  },
  {
    "artist": "Ka",
    "title": "Cold Facts",
    "featured": null,
    "producer": null,
    "audioLink": "http://www.youtube.com/watch?v=vKlCUHjU7p4"
  },
  {
    "artist": "Ka",
    "title": "No downtime",
    "featured": null,
    "producer": [
      "Ka"
    ],
    "audioLink": "http://www.youtube.com/watch?v=zeMW5JIVmxM"
  },
  {
    "artist": "Ka",
    "title": "Decisions",
    "featured": null,
    "producer": null,
    "audioLink": "http://www.youtube.com/watch?v=ylaWf9OkoTw"
  },
  {
    "artist": "Ka",
    "title": "Collage",
    "featured": null,
    "producer": null,
    "audioLink": "http://www.youtube.com/watch?v=ciiaywdKEZ4"
  },
  {
    "artist": "Ka",
    "title": "Every...",
    "featured": null,
    "producer": [
      "Ka"
    ],
    "audioLink": "http://www.youtube.com/watch?v=fIun1JrKyfM"
  },
  {
    "artist": "Ka",
    "title": "Iron Age",
    "featured": [
      "Roc Marciano"
    ],
    "producer": null,
    "audioLink": "http://www.youtube.com/watch?v=270KJcXrrpo"
  },
  {
    "artist": "Ka",
    "title": "Up Against Goliath",
    "featured": null,
    "producer": [
      "Ka"
    ],
    "audioLink": "http://www.youtube.com/watch?v=5lDm7G_Ssds"
  },
  {
    "artist": "Ka",
    "title": "Vessel",
    "featured": null,
    "producer": [
      "Ka (Kaseem Ryan)"
    ],
    "audioLink": "http://www.youtube.com/watch?v=IurFaUqDPRI"
  },
  {
    "artist": "Ka",
    "title": "Been't Ya Hell Crown",
    "featured": [
      "Boy Karim",
      "Mr. Boy"
    ],
    "producer": null,
    "audioLink": "http://www.youtube.com/watch?v=xJp4oWrfG2E"
  },
  {
    "artist": "Ka",
    "title": "You Know It's About",
    "featured": null,
    "producer": null,
    "audioLink": "http://www.youtube.com/watch?v=d1hDpufNXd0"
  },
  {
    "artist": "Ka",
    "title": "Our Father",
    "featured": null,
    "producer": null,
    "audioLink": "http://www.youtube.com/watch?v=tgsm-paBJJc"
  },
  {
    "artist": "Ka",
    "title": "Jungle",
    "featured": null,
    "producer": [
      "Ka"
    ],
    "audioLink": "http://www.youtube.com/watch?v=-OqeEBP2MQw"
  },
  {
    "artist": "Ka",
    "title": "Barring the Likeness",
    "featured": null,
    "producer": [
      "Ka"
    ],
    "audioLink": "https://soundcloud.com/brownsvilleka"
  },
  {
    "artist": "Ka",
    "title": "Nothing Is",
    "featured": null,
    "producer": [
      "Ka"
    ],
    "audioLink": null
  },
  {
    "artist": "Ka",
    "title": "Soap Box",
    "featured": [
      "Roc Marciano"
    ],
    "producer": [
      "Ka"
    ],
    "audioLink": "http://www.youtube.com/watch?v=1WbpRZiVcjc"
  },
  {
    "artist": "Ka",
    "title": "Peace Akhi",
    "featured": null,
    "producer": null,
    "audioLink": "http://www.youtube.com/watch?v=OUs3JhTdjGE"
  },
  {
    "artist": "Ka",
    "title": "Knighthood",
    "featured": null,
    "producer": null,
    "audioLink": "http://www.youtube.com/watch?v=i7p3WGLfNyQ"
  },
  {
    "artist": "Ka",
    "title": "30 Pieces of Silver",
    "featured": null,
    "producer": [
      "Ka (Kaseem Ryan)"
    ],
    "audioLink": null
  },
  {
    "artist": "Ka",
    "title": "I'm Ready",
    "featured": null,
    "producer": [
      "Ka"
    ],
    "audioLink": "http://www.youtube.com/watch?v=7iJljCb0Srk"
  },
  {
    "artist": "Ka",
    "title": "Off The Record",
    "featured": null,
    "producer": [
      "Ka"
    ],
    "audioLink": "http://www.youtube.com/watch?v=HXy0Vzp9asg"
  },
  {
    "artist": "Ka",
    "title": "The Night's Gambit - Album Art",
    "featured": null,
    "producer": null,
    "audioLink": null
  },
  {
    "artist": "Kaaris",
    "title": "Aide-moi, tue-moi",
    "featured": null,
    "producer": null,
    "audioLink": "http://www.youtube.com/watch?v=Hawf1WvYPp0"
  },
  {
    "artist": "Kaaris",
    "title": "Mets moi prem's",
    "featured": null,
    "producer": null,
    "audioLink": "http://www.youtube.com/watch?v=NjwW5PfM1m8"
  },
  {
    "artist": "Kaaris",
    "title": "Bouana",
    "featured": null,
    "producer": null,
    "audioLink": "http://www.youtube.com/watch?v=W9IEK_9YSLo"
  },
  {
    "artist": "Kaaris",
    "title": "43 ème BIMA (Pochette)",
    "featured": null,
    "producer": null,
    "audioLink": null
  },
  {
    "artist": "Kaaris",
    "title": "Qu'est-ce qui nous arrive ?",
    "featured": null,
    "producer": null,
    "audioLink": null
  },
  {
    "artist": "Kaaris",
    "title": "Bizon",
    "featured": null,
    "producer": [
      "Therapy"
    ],
    "audioLink": "http://www.youtube.com/watch?v=OrNZsmwYsv8"
  },
  {
    "artist": "Kaaris",
    "title": "Zoo",
    "featured": null,
    "producer": [
      "Therapy"
    ],
    "audioLink": "http://www.youtube.com/watch?v=xX4Pxiwti4E"
  },
  {
    "artist": "Kaaris",
    "title": "Ciroc",
    "featured": null,
    "producer": [
      "Therapy"
    ],
    "audioLink": "https://soundcloud.com/snoop-dogg-6/ciroc-kaaris"
  },
  {
    "artist": "Kaaris",
    "title": "MBM",
    "featured": null,
    "producer": [
      "Therapy"
    ],
    "audioLink": "http://www.youtube.com/watch?v=S2NE4ZTpikE"
  },
  {
    "artist": "Kaaris",
    "title": "Binks",
    "featured": null,
    "producer": [
      "Therapy"
    ],
    "audioLink": "http://www.youtube.com/watch?v=JykZ3j5lg6w"
  },
  {
    "artist": "Kaaris",
    "title": "Je bibi",
    "featured": null,
    "producer": [
      "Therapy"
    ],
    "audioLink": "http://www.youtube.com/watch?v=ODDppUSqdio"
  },
  {
    "artist": "Kaaris",
    "title": "Bouchon de liège",
    "featured": null,
    "producer": [
      "Therapy"
    ],
    "audioLink": "http://www.youtube.com/watch?v=TgHJMMXfbhE"
  },
  {
    "artist": "Kaaris",
    "title": "Paradis ou Enfer",
    "featured": null,
    "producer": [
      "Therapy"
    ],
    "audioLink": "http://www.youtube.com/watch?v=tMwdlfDZSus"
  },
  {
    "artist": "Kaaris",
    "title": "L.E.F",
    "featured": [
      "Booba"
    ],
    "producer": [
      "Therapy"
    ],
    "audioLink": "http://www.youtube.com/watch?v=lUIpv5dfITY"
  },
  {
    "artist": "Kaaris",
    "title": "Dès le départ",
    "featured": null,
    "producer": [
      "Therapy"
    ],
    "audioLink": "http://www.youtube.com/watch?v=7X5b76mdD84"
  },
  {
    "artist": "Kaaris",
    "title": "Pas de remède",
    "featured": null,
    "producer": [
      "Therapy"
    ],
    "audioLink": "http://www.youtube.com/watch?v=q3HIcjPcgKUO6g"
  },
  {
    "artist": "Kaaris",
    "title": "63",
    "featured": null,
    "producer": [
      "Therapy"
    ],
    "audioLink": "http://www.youtube.com/watch?v=3s0Zzh722BA"
  },
  {
    "artist": "Kaaris",
    "title": "Bébé",
    "featured": null,
    "producer": [
      "Therapy"
    ],
    "audioLink": "http://www.youtube.com/watch?v=RxbrXSSPgzk"
  },
  {
    "artist": "Kaaris",
    "title": "Plus Rien",
    "featured": null,
    "producer": [
      "Therapy"
    ],
    "audioLink": "http://www.youtube.com/watch?v=7-0Mw7DCUHo"
  },
  {
    "artist": "Kaaris",
    "title": "Or Noir",
    "featured": null,
    "producer": [
      "Therapy"
    ],
    "audioLink": "http://www.youtube.com/watch?v=m8LnqCSqNe4"
  },
  {
    "artist": "Kaaris",
    "title": "Tu Me Connais",
    "featured": null,
    "producer": [
      "Therapy"
    ],
    "audioLink": "http://www.youtube.com/watch?v=jbuYFrcASJA"
  },
  {
    "artist": "Kaaris",
    "title": "2 Et Demi",
    "featured": null,
    "producer": [
      "Therapy"
    ],
    "audioLink": "http://www.youtube.com/watch?v=SH0Xqli9Abc"
  },
  {
    "artist": "Kaaris",
    "title": "À La Barrière",
    "featured": null,
    "producer": [
      "Therapy"
    ],
    "audioLink": "http://www.youtube.com/watch?v=Ka7NwIMAkUo"
  },
  {
    "artist": "Kaaris",
    "title": "Or Noir (Pochette)",
    "featured": null,
    "producer": null,
    "audioLink": null
  },
  {
    "artist": "Kaaris",
    "title": "Intro",
    "featured": null,
    "producer": null,
    "audioLink": "http://www.youtube.com/watch?v=0BXsqeW47AY"
  },
  {
    "artist": "Kaaris",
    "title": "Sombre",
    "featured": null,
    "producer": [
      "Therapy"
    ],
    "audioLink": "http://www.youtube.com/watch?v=DTgRTnJ_v48"
  },
  {
    "artist": "Kaaris",
    "title": "S.E.V.R.A.N",
    "featured": null,
    "producer": [
      "Therapy"
    ],
    "audioLink": "http://www.youtube.com/watch?v=O7iWorzvlKE"
  },
  {
    "artist": "Kaaris",
    "title": "Comment je fais",
    "featured": null,
    "producer": [
      "Therapy"
    ],
    "audioLink": "http://www.youtube.com/watch?v=6LUPdDFftQI"
  },
  {
    "artist": "Kaaris",
    "title": "À l'heure",
    "featured": null,
    "producer": [
      "Therapy"
    ],
    "audioLink": "http://www.youtube.com/watch?v=OM1-PjnvZwc"
  },
  {
    "artist": "Kaaris",
    "title": "Juste",
    "featured": null,
    "producer": null,
    "audioLink": "http://www.youtube.com/watch?v=MVtBmAqs5hw"
  },
  {
    "artist": "Kaaris",
    "title": "Chargé",
    "featured": null,
    "producer": null,
    "audioLink": "http://www.youtube.com/watch?v=LPKcaidKqT8"
  },
  {
    "artist": "Kaaris",
    "title": "Pablito",
    "featured": null,
    "producer": null,
    "audioLink": "http://www.youtube.com/watch?v=evwFPu4W7zY"
  },
  {
    "artist": "Kaaris",
    "title": "Kille",
    "featured": null,
    "producer": null,
    "audioLink": "http://www.youtube.com/watch?v=AzJos1qS_4s"
  },
  {
    "artist": "Kaaris",
    "title": "Je remplis l'sac",
    "featured": null,
    "producer": null,
    "audioLink": "http://www.youtube.com/watch?v=6LUPdDFftQI"
  },
  {
    "artist": "Kaaris",
    "title": "À La Barrière",
    "featured": null,
    "producer": [
      "Therapy"
    ],
    "audioLink": "http://www.youtube.com/watch?v=Ka7NwIMAkUo"
  },
  {
    "artist": "Kaaris",
    "title": "Intro: Ram Muay",
    "featured": null,
    "producer": null,
    "audioLink": "http://www.youtube.com/watch?v=J2IUL7V7g2s"
  },
  {
    "artist": "Kaaris",
    "title": "Houdini",
    "featured": null,
    "producer": null,
    "audioLink": "http://www.youtube.com/watch?v=KXO7vUCr7qw"
  },
  {
    "artist": "Kaaris",
    "title": "L'Hôte funeste",
    "featured": null,
    "producer": null,
    "audioLink": "http://www.youtube.com/watch?v=zXr8etRCB0o"
  },
  {
    "artist": "Kaaris",
    "title": "Bon qu'à ça",
    "featured": null,
    "producer": null,
    "audioLink": "http://www.youtube.com/watch?v=sT98QaRP8_4"
  },
  {
    "artist": "Kaaris",
    "title": "L'oeil du mur",
    "featured": null,
    "producer": null,
    "audioLink": "http://www.youtube.com/watch?v=mvH1AozLobI"
  },
  {
    "artist": "Kaaris",
    "title": "Lourd Lourd",
    "featured": null,
    "producer": null,
    "audioLink": "http://www.youtube.com/watch?v=kNhK1vD0vlA"
  },
  {
    "artist": "Booba",
    "title": "Criminelle league",
    "featured": [
      "Kaaris"
    ],
    "producer": [
      "Therapy"
    ],
    "audioLink": "http://www.youtube.com/watch?v=kXPDOroeg8Q"
  },
  {
    "artist": "Kaaris",
    "title": "Le Légiste",
    "featured": null,
    "producer": null,
    "audioLink": "http://www.youtube.com/watch?v=5Bkr28CenKM"
  },
  {
    "artist": "Kaaris",
    "title": "Cayman",
    "featured": null,
    "producer": null,
    "audioLink": "http://www.youtube.com/watch?v=p8fUiXGfYRA"
  },
  {
    "artist": "Kaaris",
    "title": "Hémophiles",
    "featured": null,
    "producer": null,
    "audioLink": "http://www.youtube.com/watch?v=3wOiAuUGVj0"
  },
  {
    "artist": "Kaaris",
    "title": "Un caillou sur la langue",
    "featured": null,
    "producer": null,
    "audioLink": "http://www.youtube.com/watch?v=v61Trpt7ch8"
  },
  {
    "artist": "Kaaris",
    "title": "Super Nova",
    "featured": null,
    "producer": [
      "Therapy"
    ],
    "audioLink": "http://www.youtube.com/watch?v=n0Ac9FpKHm8"
  },
  {
    "artist": "Kaaris",
    "title": "Z.E.R.O (Pochette)",
    "featured": null,
    "producer": null,
    "audioLink": null
  },
  {
    "artist": "KaBi",
    "title": "Im The Best Prod. By Dj Spoonz",
    "featured": [
      "Dizzy",
      "JLuca$",
      "Lew Bonds",
      "Quaa Lovee",
      "Shizz"
    ],
    "producer": null,
    "audioLink": "http://www.youtube.com/watch?v=nfW-sPRUj7w"
  },
  {
    "artist": "KaBi",
    "title": "Under The Moonlight",
    "featured": [
      "Lew Bonds"
    ],
    "producer": null,
    "audioLink": "http://www.youtube.com/watch?v=TkIJDZJZ3b0"
  },
  {
    "artist": "KaBi",
    "title": "A.A.A",
    "featured": [
      "Dev",
      "T-Will"
    ],
    "producer": null,
    "audioLink": null
  },
  {
    "artist": "KaBi",
    "title": "Death Of Fresh",
    "featured": [
      "Mr Parker"
    ],
    "producer": null,
    "audioLink": "http://www.youtube.com/watch?v=Q_qWjehBq2w"
  },
  {
    "artist": "KaBi",
    "title": "No Mercy",
    "featured": [
      "Hieness",
      "T-Will"
    ],
    "producer": null,
    "audioLink": null
  },
  {
    "artist": "KaBi",
    "title": "As It Blooms",
    "featured": [
      "Savoy LaShai"
    ],
    "producer": null,
    "audioLink": "http://www.youtube.com/watch?v=01jabA4i5wk"
  },
  {
    "artist": "KaBi",
    "title": "Go Girl",
    "featured": [
      "Yahieness"
    ],
    "producer": [
      "Taylor Made Beats"
    ],
    "audioLink": "https://soundcloud.com/kabi23/go-girl-kabi-x-yahieness"
  }
]